microbit_wings/__init__.py
microbit_wings/config.py
microbit_wings/image_creator.py
microbit_wings/images.py
microbit_wings/microbit.py
microbit_wings/toolbox.py
microbit_wings-1.0.1.dist-info/LICENSE.txt
microbit_wings-1.0.1.dist-info/METADATA
microbit_wings-1.0.1.dist-info/WHEEL
microbit_wings-1.0.1.dist-info/top_level.txt
microbit_wings-1.0.1.dist-info/RECORD
